{
  "project_info": {
    "project_number": "788744506991",
    "project_id": "ttanggul-d8e19",
    "storage_bucket": "ttanggul-d8e19.firebasestorage.app"
  },
  "client": [
    {
      "client_info": {
        "mobilesdk_app_id": "1:788744506991:android:b26d3e9cb84e7c2705479a",
        "android_client_info": {
          "package_name": "com.anonymous.ddanggulapp"
        }
      },
      "oauth_client": [
        {
          "client_id": "788744506991-l49kcmjf44f62g53ojm1ttvoqdb031qu.apps.googleusercontent.com",
          "client_type": 1,
          "android_info": {
            "package_name": "com.anonymous.ddanggulapp",
            "certificate_hash": "b4d62593a5930b372a164331ff56eed4d8d86d44"
          }
        },
        {
          "client_id": "788744506991-pjrkcpf2i1hi8331fgekpbq9307ka8da.apps.googleusercontent.com",
          "client_type": 3
        }
      ],
      "api_key": [
        {
          "current_key": "AIzaSyBGc1w6Hd79Wg0g1vSGuS5KUUaVCSdTDQc"
        }
      ],
      "services": {
        "appinvite_service": {
          "other_platform_oauth_client": [
            {
              "client_id": "788744506991-pjrkcpf2i1hi8331fgekpbq9307ka8da.apps.googleusercontent.com",
              "client_type": 3
            }
          ]
        }
      }
    }
  ],
  "configuration_version": "1"
}